[
    {
        "arguments": [
            "cc",
            "-c",
            "-Wall",
            "-Werror",
            "-Wno-unused-result",
            "-Wno-unused-function",
            "-fstrict-aliasing",
            "-Wstrict-aliasing",
            "-g",
            "-I./",
            "-I../",
            "-I../third-party/.objs/include",
            "-Os",
            "-include",
            "../../base.h",
            "-include",
            "../../defs.h",
            "-o",
            ".objs/asm.o",
            "asm.c"
        ],
        "directory": "/home/gfeng/go/src/github.com/neuvector/neuvector/dp/utils",
        "file": "asm.c"
    },
    {
        "arguments": [
            "cc",
            "-c",
            "-Wall",
            "-Werror",
            "-Wno-unused-result",
            "-Wno-unused-function",
            "-fstrict-aliasing",
            "-Wstrict-aliasing",
            "-g",
            "-I./",
            "-I../",
            "-I../third-party/.objs/include",
            "-Os",
            "-include",
            "../../base.h",
            "-include",
            "../../defs.h",
            "-o",
            ".objs/bitmap.o",
            "bitmap.c"
        ],
        "directory": "/home/gfeng/go/src/github.com/neuvector/neuvector/dp/utils",
        "file": "bitmap.c"
    },
    {
        "arguments": [
            "cc",
            "-c",
            "-Wall",
            "-Werror",
            "-Wno-unused-result",
            "-Wno-unused-function",
            "-fstrict-aliasing",
            "-Wstrict-aliasing",
            "-g",
            "-I./",
            "-I../",
            "-I../third-party/.objs/include",
            "-Os",
            "-include",
            "../../base.h",
            "-include",
            "../../defs.h",
            "-o",
            ".objs/tree.o",
            "tree.c"
        ],
        "directory": "/home/gfeng/go/src/github.com/neuvector/neuvector/dp/utils",
        "file": "tree.c"
    },
    {
        "arguments": [
            "cc",
            "-c",
            "-Wall",
            "-Werror",
            "-Wno-unused-result",
            "-Wno-unused-function",
            "-fstrict-aliasing",
            "-Wstrict-aliasing",
            "-g",
            "-I./",
            "-I../",
            "-I../third-party/.objs/include",
            "-Os",
            "-include",
            "../../base.h",
            "-include",
            "../../defs.h",
            "-o",
            ".objs/timer_wheel.o",
            "timer_wheel.c"
        ],
        "directory": "/home/gfeng/go/src/github.com/neuvector/neuvector/dp/utils",
        "file": "timer_wheel.c"
    },
    {
        "arguments": [
            "cc",
            "-c",
            "-Wall",
            "-Werror",
            "-Wno-unused-result",
            "-Wno-unused-function",
            "-fstrict-aliasing",
            "-Wstrict-aliasing",
            "-g",
            "-I./",
            "-I../",
            "-I../third-party/.objs/include",
            "-Os",
            "-include",
            "../../base.h",
            "-include",
            "../../defs.h",
            "-o",
            ".objs/helper.o",
            "helper.c"
        ],
        "directory": "/home/gfeng/go/src/github.com/neuvector/neuvector/dp/utils",
        "file": "helper.c"
    },
    {
        "arguments": [
            "cc",
            "-c",
            "-Wall",
            "-Werror",
            "-Wno-unused-result",
            "-Wno-unused-function",
            "-fstrict-aliasing",
            "-Wstrict-aliasing",
            "-g",
            "-I./",
            "-I../",
            "-I../third-party/.objs/include",
            "-Os",
            "-include",
            "../../base.h",
            "-include",
            "../../defs.h",
            "-o",
            ".objs/rcu_map.o",
            "rcu_map.c"
        ],
        "directory": "/home/gfeng/go/src/github.com/neuvector/neuvector/dp/utils",
        "file": "rcu_map.c"
    },
    {
        "arguments": [
            "cc",
            "-c",
            "-Wall",
            "-Werror",
            "-Wno-unused-result",
            "-Wno-unused-function",
            "-fstrict-aliasing",
            "-Wstrict-aliasing",
            "-g",
            "-I./",
            "-I../",
            "-I../third-party/.objs/include",
            "-Os",
            "-include",
            "../../base.h",
            "-include",
            "../../defs.h",
            "-o",
            ".objs/asn1.o",
            "asn1.c"
        ],
        "directory": "/home/gfeng/go/src/github.com/neuvector/neuvector/dp/utils",
        "file": "asn1.c"
    },
    {
        "arguments": [
            "cc",
            "-c",
            "-Wall",
            "-Werror",
            "-Wno-unused-result",
            "-Wno-unused-function",
            "-fstrict-aliasing",
            "-Wstrict-aliasing",
            "-g",
            "-I./",
            "-I../",
            "-I../third-party/.objs/include",
            "-Os",
            "-include",
            "../../base.h",
            "-include",
            "../../defs.h",
            "-o",
            ".objs/timer_queue.o",
            "timer_queue.c"
        ],
        "directory": "/home/gfeng/go/src/github.com/neuvector/neuvector/dp/utils",
        "file": "timer_queue.c"
    }
]