[
    {
        "arguments": [
            "cc",
            "-c",
            "-Wall",
            "-Werror",
            "-Wno-unused-result",
            "-Wno-unused-function",
            "-fstrict-aliasing",
            "-Wstrict-aliasing",
            "-g",
            "-I./",
            "-I../../",
            "-I../../third-party/.objs/include",
            "-Os",
            "-include",
            "../../../base.h",
            "-include",
            "../../../defs.h",
            "-o",
            ".objs/dpi_sigopt_basic.o",
            "dpi_sigopt_basic.c"
        ],
        "directory": "/home/gfeng/go/src/github.com/neuvector/neuvector/dp/dpi/sig",
        "file": "dpi_sigopt_basic.c"
    },
    {
        "arguments": [
            "cc",
            "-c",
            "-Wall",
            "-Werror",
            "-Wno-unused-result",
            "-Wno-unused-function",
            "-fstrict-aliasing",
            "-Wstrict-aliasing",
            "-g",
            "-I./",
            "-I../../",
            "-I../../third-party/.objs/include",
            "-Os",
            "-include",
            "../../../base.h",
            "-include",
            "../../../defs.h",
            "-o",
            ".objs/dpi_hs_search.o",
            "dpi_hs_search.c"
        ],
        "directory": "/home/gfeng/go/src/github.com/neuvector/neuvector/dp/dpi/sig",
        "file": "dpi_hs_search.c"
    },
    {
        "arguments": [
            "cc",
            "-c",
            "-Wall",
            "-Werror",
            "-Wno-unused-result",
            "-Wno-unused-function",
            "-fstrict-aliasing",
            "-Wstrict-aliasing",
            "-g",
            "-I./",
            "-I../../",
            "-I../../third-party/.objs/include",
            "-Os",
            "-include",
            "../../../base.h",
            "-include",
            "../../../defs.h",
            "-o",
            ".objs/dpi_sigopt_pcre.o",
            "dpi_sigopt_pcre.c"
        ],
        "directory": "/home/gfeng/go/src/github.com/neuvector/neuvector/dp/dpi/sig",
        "file": "dpi_sigopt_pcre.c"
    },
    {
        "arguments": [
            "cc",
            "-c",
            "-Wall",
            "-Werror",
            "-Wno-unused-result",
            "-Wno-unused-function",
            "-fstrict-aliasing",
            "-Wstrict-aliasing",
            "-g",
            "-I./",
            "-I../../",
            "-I../../third-party/.objs/include",
            "-Os",
            "-include",
            "../../../base.h",
            "-include",
            "../../../defs.h",
            "-o",
            ".objs/dpi_search.o",
            "dpi_search.c"
        ],
        "directory": "/home/gfeng/go/src/github.com/neuvector/neuvector/dp/dpi/sig",
        "file": "dpi_search.c"
    },
    {
        "arguments": [
            "cc",
            "-c",
            "-Wall",
            "-Werror",
            "-Wno-unused-result",
            "-Wno-unused-function",
            "-fstrict-aliasing",
            "-Wstrict-aliasing",
            "-g",
            "-I./",
            "-I../../",
            "-I../../third-party/.objs/include",
            "-Os",
            "-include",
            "../../../base.h",
            "-include",
            "../../../defs.h",
            "-o",
            ".objs/dpi_hyperscan_common.o",
            "dpi_hyperscan_common.c"
        ],
        "directory": "/home/gfeng/go/src/github.com/neuvector/neuvector/dp/dpi/sig",
        "file": "dpi_hyperscan_common.c"
    },
    {
        "arguments": [
            "cc",
            "-c",
            "-Wall",
            "-Werror",
            "-Wno-unused-result",
            "-Wno-unused-function",
            "-fstrict-aliasing",
            "-Wstrict-aliasing",
            "-g",
            "-I./",
            "-I../../",
            "-I../../third-party/.objs/include",
            "-Os",
            "-include",
            "../../../base.h",
            "-include",
            "../../../defs.h",
            "-o",
            ".objs/dpi_sig.o",
            "dpi_sig.c"
        ],
        "directory": "/home/gfeng/go/src/github.com/neuvector/neuvector/dp/dpi/sig",
        "file": "dpi_sig.c"
    }
]